LICENSE.txt
MANIFEST.in
README.txt
setup.py
bin/swiftwal
swiftwal/__init__.py
swiftwal/commands.py
swiftwal/swiftconnection.py
swiftwal.egg-info/PKG-INFO
swiftwal.egg-info/SOURCES.txt
swiftwal.egg-info/dependency_links.txt
swiftwal.egg-info/entry_points.txt
swiftwal.egg-info/requires.txt
swiftwal.egg-info/top_level.txt
swiftwal.egg-info/zip-safe