Metadata-Version: 1.1
Name: swiftwal
Version: 0.2.2
Summary: PostgreSQL backups, WAL archiving & PITR to OpenStack Swift
Home-page: https://launchpad.net/swiftwal
Author: Stuart Bishop
Author-email: stuart.bishop@canonical.com
License: UNKNOWN
Keywords: postgresql postgres wal pitr backup
Platform: UNKNOWN
Classifier: Development Status :: 3 - Alpha
Classifier: License :: OSI Approved :: GNU General Public License v3 (GPLv3)
Classifier: Environment :: Console
Classifier: Environment :: OpenStack
Classifier: Intended Audience :: System Administrators
Classifier: Natural Language :: English
Classifier: Operating System :: OS Independent
Classifier: Programming Language :: Python
Classifier: Programming Language :: Python :: 2
Classifier: Programming Language :: Python :: 2.6
Classifier: Programming Language :: Python :: 2.7
Classifier: Topic :: Database
Classifier: Topic :: System :: Archiving :: Backup
Classifier: Topic :: System :: Recovery Tools
Classifier: Topic :: System :: Systems Administration
